[
    {
        "imgSrc": "~/src/Pages/Images/SSMA.png",
        "title": "Student Services Management App",
        "description": "A mobile application that allows students to manage their reservations of university services with a click of a button.",
        "skills": [
            "Volley"
        ],
        "githubLink": "https://github.com/ninidhiaeddine/student-services-management-mobile"
    },
    {
        "imgSrc": "~/src/Pages/Images/GymManagement.png",
        "title": "Gym Management App",
        "description": "A mobile application that allows students to manage their reservations of university services with a click of a button.",
        "skills": [
            "SQLite"
        ],
        "githubLink": "https://github.com/ninidhiaeddine/FatehFitness"
    }
]